pycottas/__init__.py
pycottas/__main__.py
pycottas/_version.py
pycottas/constants.py
pycottas/cottas_document.py
pycottas/cottas_store.py
pycottas/tp_translator.py
pycottas/types.py
pycottas/utils.py
pycottas-1.1.0.dist-info/METADATA
pycottas-1.1.0.dist-info/WHEEL
pycottas-1.1.0.dist-info/licenses/LICENSE
pycottas-1.1.0.dist-info/RECORD
