Metadata-Version: 2.4
Name: pycottas
Version: 1.1.0
Summary: Python COTTAS library for compressing and querying RDF.
Project-URL: Documentation, https://pycottas.readthedocs.io
Project-URL: Source, https://github.com/arenas-guerrero-julian/pycottas
Project-URL: Tracker, https://github.com/arenas-guerrero-julian/pycottas/issues
Project-URL: History, https://github.com/arenas-guerrero-julian/pycottas/releases
Author-email: Julián Arenas-Guerrero <julian.arenas.guerrero@upm.es>
License-Expression: Apache-2.0
License-File: LICENSE
Keywords: Apache Parquet,Data Compression,Knowledge Graph,RDF
Classifier: Development Status :: 5 - Production/Stable
Classifier: Environment :: Console
Classifier: Intended Audience :: Information Technology
Classifier: Intended Audience :: Science/Research
Classifier: License :: OSI Approved :: Apache Software License
Classifier: Operating System :: OS Independent
Classifier: Programming Language :: Python :: 3
Classifier: Programming Language :: Python :: 3.8
Classifier: Programming Language :: Python :: 3.9
Classifier: Programming Language :: Python :: 3.10
Classifier: Programming Language :: Python :: 3.11
Classifier: Programming Language :: Python :: 3.12
Classifier: Programming Language :: Python :: 3.13
Classifier: Topic :: Database
Classifier: Topic :: Scientific/Engineering
Classifier: Topic :: Utilities
Requires-Python: >=3.8
Requires-Dist: duckdb<2.0.0,>=1.2.2
Requires-Dist: pandas<3.0.0,>=2.0.0
Requires-Dist: pyoxigraph==0.3.18
Requires-Dist: rdflib<8.0.0,>=7.0.0
